PValidator/__init__.py
PValidator/exceptions.py
PValidator/services.py
PValidator-0.1.0.dist-info/LICENSE
PValidator-0.1.0.dist-info/METADATA
PValidator-0.1.0.dist-info/WHEEL
PValidator-0.1.0.dist-info/top_level.txt
PValidator-0.1.0.dist-info/RECORD
